qspec/__init__.py
qspec/algebra.py
qspec/physics.py
qspec/qtypes.py
qspec/stats.py
qspec/tools.py
qspec/_cpp/__init__.py
qspec/_cpp/_cpp.py
qspec/_cpp/src/__init__.py
qspec/_cpp/src/qspec_cpp/__init__.py
qspec/_cpp/src/qspec_cpp/Release/__init__.py
qspec/_cpp/src/qspec_cpp/Release/qspec_cpp.dll
qspec/_cpp/src/qspec_cpp/x64/__init__.py
qspec/_cpp/src/qspec_cpp/x64/Release/__init__.py
qspec/_cpp/src/qspec_cpp/x64/Release/qspec_cpp.dll
qspec/analyze/__init__.py
qspec/analyze/_analyze.py
qspec/analyze/_analyze_cpp.py
qspec/models/__init__.py
qspec/models/_base.py
qspec/models/_convolved.py
qspec/models/_fit.py
qspec/models/_helper.py
qspec/models/_spectrum.py
qspec/models/_splitter.py
qspec/simulate/__init__.py
qspec/simulate/_simulate.py
qspec/simulate/_simulate_cpp.py
qspec-0.4.2.dist-info/licenses/LICENSE
qspec-0.4.2.dist-info/METADATA
qspec-0.4.2.dist-info/WHEEL
qspec-0.4.2.dist-info/top_level.txt
qspec-0.4.2.dist-info/RECORD
