Metadata-Version: 2.4
Name: qspec
Version: 0.4.2
Summary: Physics toolbox for laser spectroscopy
Author-email: Patrick Müller <pmueller@physics.ucla.edu>
License: MIT License
Project-URL: homepage, https://patmlr.github.io/qspec/
Project-URL: documentation, https://patmlr.github.io/qspec/doc/doc.html
Project-URL: download, https://pypi.org/project/qspec/#files
Project-URL: source, https://github.com/patmlr/qspec
Project-URL: tracker, https://github.com/patmlr/qspec/issues
Keywords: physics,simulation,data analysis,atomic structure,laser spectroscopy,laser cooling,coherent interaction,quantum computing
Classifier: Development Status :: 4 - Beta
Classifier: Intended Audience :: Science/Research
Classifier: License :: OSI Approved :: MIT License
Classifier: Operating System :: Microsoft :: Windows
Classifier: Programming Language :: C++
Classifier: Programming Language :: Python :: 3
Classifier: Programming Language :: Python :: 3 :: Only
Classifier: Topic :: Scientific/Engineering :: Physics
Requires-Python: >=3.9
License-File: LICENSE
Requires-Dist: matplotlib
Requires-Dist: numpy>=2.0.2
Requires-Dist: scipy>=1.13.1
Requires-Dist: sympy
Dynamic: license-file
